{
  "version": "1.0",
  "encoding": "utf-8",
  "adp": {
    "totalPicks": "556",
    "timestamp": "1779386072",
    "player": [
      {
        "id": "17472",
        "draftsSelectedIn": "1172",
        "maxPick": "48",
        "averagePick": "2.40",
        "minPick": "1",
        "draftSelPct": "99",
        "rank": "1"
      },
      {
        "maxPick": "8",
        "averagePick": "2.58",
        "draftsSelectedIn": "64",
        "id": "16161",
        "draftSelPct": "5",
        "minPick": "1",
        "rank": "2"
      },
      {
        "rank": "3",
        "draftSelPct": "5",
        "minPick": "1",
        "maxPick": "12",
        "averagePick": "2.97",
        "draftsSelectedIn": "63",
        "id": "16162"
      },
      {
        "rank": "4",
        "draftsSelectedIn": "65",
        "averagePick": "4.68",
        "maxPick": "10",
        "id": "15281",
        "draftSelPct": "5",
        "minPick": "1"
      },
      {
        "rank": "5",
        "draftSelPct": "97",
        "minPick": "1",
        "draftsSelectedIn": "1158",
        "maxPick": "119",
        "averagePick": "5.34",
        "id": "17497"
      },
      {
        "draftSelPct": "98",
        "minPick": "1",
        "draftsSelectedIn": "1168",
        "maxPick": "137",
        "averagePick": "6.94",
        "id": "17498",
        "rank": "6"
      },
      {
        "minPick": "1",
        "draftSelPct": "105",
        "id": "17473",
        "draftsSelectedIn": "1248",
        "maxPick": "91",
        "averagePick": "7.02",
        "rank": "7"
      },
      {
        "minPick": "2",
        "draftSelPct": "5",
        "id": "16211",
        "averagePick": "7.66",
        "maxPick": "17",
        "draftsSelectedIn": "61",
        "rank": "8"
      },
      {
        "rank": "9",
        "minPick": "1",
        "draftSelPct": "100",
        "id": "17499",
        "draftsSelectedIn": "1187",
        "maxPick": "142",
        "averagePick": "7.72"
      },
      {
        "rank": "10",
        "draftSelPct": "5",
        "minPick": "1",
        "averagePick": "7.97",
        "maxPick": "27",
        "draftsSelectedIn": "66",
        "id": "15794"
      },
      {
        "rank": "11",
        "id": "17462",
        "maxPick": "176",
        "averagePick": "8.08",
        "draftsSelectedIn": "1207",
        "minPick": "1",
        "draftSelPct": "102"
      },
      {
        "id": "16185",
        "draftsSelectedIn": "64",
        "averagePick": "8.31",
        "maxPick": "13",
        "minPick": "2",
        "draftSelPct": "5",
        "rank": "12"
      },
      {
        "maxPick": "49",
        "averagePick": "9.74",
        "draftsSelectedIn": "62",
        "id": "13130",
        "draftSelPct": "5",
        "minPick": "1",
        "rank": "13"
      },
      {
        "minPick": "1",
        "draftSelPct": "5",
        "id": "16641",
        "draftsSelectedIn": "65",
        "maxPick": "60",
        "averagePick": "9.88",
        "rank": "14"
      },
      {
        "rank": "15",
        "draftSelPct": "100",
        "minPick": "2",
        "draftsSelectedIn": "1191",
        "averagePick": "10.23",
        "maxPick": "168",
        "id": "17501"
      },
      {
        "maxPick": "240",
        "averagePick": "10.29",
        "draftsSelectedIn": "1211",
        "id": "17543",
        "draftSelPct": "102",
        "minPick": "1",
        "rank": "16"
      },
      {
        "rank": "17",
        "draftSelPct": "5",
        "minPick": "3",
        "draftsSelectedIn": "61",
        "averagePick": "11.38",
        "maxPick": "37",
        "id": "14802"
      },
      {
        "rank": "18",
        "draftSelPct": "48",
        "minPick": "1",
        "averagePick": "11.75",
        "maxPick": "143",
        "draftsSelectedIn": "578",
        "id": "17557"
      },
      {
        "rank": "19",
        "minPick": "4",
        "draftSelPct": "5",
        "id": "15287",
        "maxPick": "21",
        "averagePick": "11.95",
        "draftsSelectedIn": "66"
      },
      {
        "rank": "20",
        "draftSelPct": "102",
        "minPick": "1",
        "draftsSelectedIn": "1217",
        "maxPick": "197",
        "averagePick": "12.03",
        "id": "17502"
      },
      {
        "rank": "21",
        "draftSelPct": "102",
        "minPick": "2",
        "averagePick": "13.36",
        "maxPick": "233",
        "draftsSelectedIn": "1212",
        "id": "17544"
      },
      {
        "maxPick": "242",
        "averagePick": "14.87",
        "draftsSelectedIn": "1164",
        "id": "17500",
        "draftSelPct": "98",
        "minPick": "6",
        "rank": "22"
      },
      {
        "rank": "23",
        "id": "16167",
        "draftsSelectedIn": "65",
        "maxPick": "31",
        "averagePick": "15.12",
        "minPick": "2",
        "draftSelPct": "5"
      },
      {
        "rank": "24",
        "minPick": "3",
        "draftSelPct": "5",
        "id": "17042",
        "draftsSelectedIn": "63",
        "maxPick": "34",
        "averagePick": "15.38"
      },
      {
        "rank": "25",
        "draftsSelectedIn": "62",
        "averagePick": "15.92",
        "maxPick": "37",
        "id": "15715",
        "draftSelPct": "5",
        "minPick": "8"
      },
      {
        "draftsSelectedIn": "1177",
        "averagePick": "17.08",
        "maxPick": "245",
        "id": "17477",
        "draftSelPct": "99",
        "minPick": "2",
        "rank": "26"
      },
      {
        "rank": "27",
        "id": "17556",
        "draftsSelectedIn": "576",
        "maxPick": "188",
        "averagePick": "17.48",
        "minPick": "2",
        "draftSelPct": "48"
      },
      {
        "rank": "28",
        "minPick": "5",
        "draftSelPct": "97",
        "id": "17512",
        "maxPick": "337",
        "averagePick": "18.08",
        "draftsSelectedIn": "1154"
      },
      {
        "rank": "29",
        "id": "14832",
        "draftsSelectedIn": "64",
        "maxPick": "29",
        "averagePick": "18.09",
        "minPick": "7",
        "draftSelPct": "5"
      },
      {
        "rank": "30",
        "draftSelPct": "5",
        "minPick": "9",
        "maxPick": "32",
        "averagePick": "18.43",
        "draftsSelectedIn": "60",
        "id": "14836"
      },
      {
        "rank": "31",
        "minPick": "5",
        "draftSelPct": "47",
        "id": "17558",
        "maxPick": "218",
        "averagePick": "19.31",
        "draftsSelectedIn": "565"
      },
      {
        "rank": "32",
        "draftSelPct": "99",
        "minPick": "2",
        "draftsSelectedIn": "1181",
        "maxPick": "218",
        "averagePick": "20.11",
        "id": "17463"
      },
      {
        "draftSelPct": "102",
        "minPick": "3",
        "maxPick": "289",
        "averagePick": "20.59",
        "draftsSelectedIn": "1211",
        "id": "17506",
        "rank": "33"
      },
      {
        "rank": "34",
        "id": "17503",
        "draftsSelectedIn": "1186",
        "maxPick": "314",
        "averagePick": "20.59",
        "minPick": "3",
        "draftSelPct": "100"
      },
      {
        "id": "17476",
        "maxPick": "292",
        "averagePick": "21.61",
        "draftsSelectedIn": "1108",
        "minPick": "4",
        "draftSelPct": "93",
        "rank": "35"
      },
      {
        "rank": "36",
        "draftsSelectedIn": "564",
        "maxPick": "191",
        "averagePick": "22.41",
        "id": "17586",
        "draftSelPct": "47",
        "minPick": "5"
      },
      {
        "rank": "37",
        "draftsSelectedIn": "568",
        "averagePick": "22.53",
        "maxPick": "172",
        "id": "17563",
        "draftSelPct": "48",
        "minPick": "2"
      },
      {
        "rank": "38",
        "maxPick": "176",
        "averagePick": "22.62",
        "draftsSelectedIn": "569",
        "id": "17551",
        "draftSelPct": "48",
        "minPick": "2"
      },
      {
        "id": "17514",
        "averagePick": "22.64",
        "maxPick": "402",
        "draftsSelectedIn": "1200",
        "minPick": "4",
        "draftSelPct": "101",
        "rank": "39"
      },
      {
        "minPick": "12",
        "draftSelPct": "5",
        "id": "17044",
        "draftsSelectedIn": "64",
        "averagePick": "23.27",
        "maxPick": "46",
        "rank": "40"
      },
      {
        "rank": "41",
        "minPick": "3",
        "draftSelPct": "5",
        "id": "16581",
        "draftsSelectedIn": "63",
        "averagePick": "25.67",
        "maxPick": "76"
      },
      {
        "minPick": "3",
        "draftSelPct": "47",
        "id": "17550",
        "draftsSelectedIn": "564",
        "maxPick": "167",
        "averagePick": "25.92",
        "rank": "42"
      },
      {
        "draftsSelectedIn": "1188",
        "averagePick": "26.62",
        "maxPick": "423",
        "id": "17474",
        "draftSelPct": "100",
        "minPick": "4",
        "rank": "43"
      },
      {
        "draftSelPct": "100",
        "minPick": "5",
        "draftsSelectedIn": "1193",
        "maxPick": "368",
        "averagePick": "27.73",
        "id": "17482",
        "rank": "44"
      },
      {
        "rank": "45",
        "minPick": "8",
        "draftSelPct": "5",
        "id": "15751",
        "averagePick": "27.73",
        "maxPick": "49",
        "draftsSelectedIn": "63"
      },
      {
        "draftsSelectedIn": "1198",
        "averagePick": "28.13",
        "maxPick": "405",
        "id": "17520",
        "draftSelPct": "101",
        "minPick": "4",
        "rank": "46"
      },
      {
        "rank": "47",
        "minPick": "4",
        "draftSelPct": "5",
        "id": "14777",
        "maxPick": "75",
        "averagePick": "28.56",
        "draftsSelectedIn": "64"
      },
      {
        "rank": "48",
        "maxPick": "287",
        "averagePick": "28.58",
        "draftsSelectedIn": "1176",
        "id": "17509",
        "draftSelPct": "99",
        "minPick": "6"
      },
      {
        "id": "17104",
        "maxPick": "100",
        "averagePick": "28.83",
        "draftsSelectedIn": "63",
        "minPick": "6",
        "draftSelPct": "5",
        "rank": "49"
      },
      {
        "rank": "50",
        "minPick": "3",
        "draftSelPct": "5",
        "id": "14783",
        "averagePick": "29.03",
        "maxPick": "77",
        "draftsSelectedIn": "62"
      },
      {
        "minPick": "7",
        "draftSelPct": "45",
        "id": "17560",
        "averagePick": "30.22",
        "maxPick": "355",
        "draftsSelectedIn": "536",
        "rank": "51"
      },
      {
        "draftSelPct": "96",
        "minPick": "5",
        "averagePick": "30.88",
        "maxPick": "391",
        "draftsSelectedIn": "1144",
        "id": "17478",
        "rank": "52"
      },
      {
        "rank": "53",
        "minPick": "7",
        "draftSelPct": "98",
        "id": "17511",
        "maxPick": "404",
        "averagePick": "31.13",
        "draftsSelectedIn": "1168"
      },
      {
        "draftSelPct": "5",
        "minPick": "17",
        "draftsSelectedIn": "60",
        "averagePick": "31.27",
        "maxPick": "62",
        "id": "16194",
        "rank": "54"
      },
      {
        "minPick": "6",
        "draftSelPct": "47",
        "id": "17576",
        "maxPick": "200",
        "averagePick": "31.41",
        "draftsSelectedIn": "559",
        "rank": "55"
      },
      {
        "rank": "56",
        "id": "17507",
        "draftsSelectedIn": "1109",
        "averagePick": "31.47",
        "maxPick": "406",
        "minPick": "7",
        "draftSelPct": "93"
      },
      {
        "id": "17485",
        "maxPick": "395",
        "averagePick": "31.80",
        "draftsSelectedIn": "1175",
        "minPick": "3",
        "draftSelPct": "99",
        "rank": "57"
      },
      {
        "maxPick": "80",
        "averagePick": "33.45",
        "draftsSelectedIn": "60",
        "id": "14073",
        "draftSelPct": "5",
        "minPick": "16",
        "rank": "58"
      },
      {
        "rank": "59",
        "id": "17547",
        "draftsSelectedIn": "1154",
        "maxPick": "456",
        "averagePick": "33.56",
        "minPick": "8",
        "draftSelPct": "97"
      },
      {
        "rank": "60",
        "draftsSelectedIn": "539",
        "averagePick": "33.74",
        "maxPick": "384",
        "id": "17589",
        "draftSelPct": "45",
        "minPick": "10"
      },
      {
        "rank": "61",
        "minPick": "17",
        "draftSelPct": "5",
        "id": "15708",
        "draftsSelectedIn": "62",
        "averagePick": "33.84",
        "maxPick": "67"
      },
      {
        "id": "16579",
        "draftsSelectedIn": "63",
        "averagePick": "33.98",
        "maxPick": "78",
        "minPick": "2",
        "draftSelPct": "5",
        "rank": "62"
      },
      {
        "id": "15711",
        "maxPick": "57",
        "averagePick": "34.15",
        "draftsSelectedIn": "62",
        "minPick": "18",
        "draftSelPct": "5",
        "rank": "63"
      },
      {
        "rank": "64",
        "minPick": "3",
        "draftSelPct": "87",
        "id": "17466",
        "draftsSelectedIn": "1038",
        "maxPick": "201",
        "averagePick": "34.21"
      },
      {
        "id": "17508",
        "averagePick": "35.85",
        "maxPick": "426",
        "draftsSelectedIn": "1164",
        "minPick": "7",
        "draftSelPct": "98",
        "rank": "65"
      },
      {
        "draftSelPct": "43",
        "minPick": "10",
        "maxPick": "401",
        "averagePick": "36.54",
        "draftsSelectedIn": "517",
        "id": "17571",
        "rank": "66"
      },
      {
        "rank": "67",
        "id": "17567",
        "draftsSelectedIn": "1110",
        "averagePick": "36.89",
        "maxPick": "553",
        "minPick": "9",
        "draftSelPct": "93"
      },
      {
        "draftSelPct": "96",
        "minPick": "9",
        "draftsSelectedIn": "1145",
        "averagePick": "37.48",
        "maxPick": "412",
        "id": "17481",
        "rank": "68"
      },
      {
        "rank": "69",
        "minPick": "11",
        "draftSelPct": "95",
        "id": "17505",
        "averagePick": "38.64",
        "maxPick": "400",
        "draftsSelectedIn": "1134"
      },
      {
        "rank": "70",
        "id": "17032",
        "averagePick": "38.66",
        "maxPick": "89",
        "draftsSelectedIn": "62",
        "minPick": "16",
        "draftSelPct": "5"
      },
      {
        "draftsSelectedIn": "63",
        "averagePick": "38.92",
        "maxPick": "69",
        "id": "15290",
        "draftSelPct": "5",
        "minPick": "9",
        "rank": "71"
      },
      {
        "minPick": "9",
        "draftSelPct": "93",
        "id": "17517",
        "draftsSelectedIn": "1109",
        "maxPick": "408",
        "averagePick": "39.61",
        "rank": "72"
      },
      {
        "minPick": "7",
        "draftSelPct": "90",
        "id": "17607",
        "maxPick": "436",
        "averagePick": "39.94",
        "draftsSelectedIn": "1075",
        "rank": "73"
      },
      {
        "id": "17468",
        "averagePick": "40.27",
        "maxPick": "242",
        "draftsSelectedIn": "967",
        "minPick": "10",
        "draftSelPct": "81",
        "rank": "74"
      },
      {
        "rank": "75",
        "draftsSelectedIn": "1095",
        "maxPick": "351",
        "averagePick": "41.99",
        "id": "17599",
        "draftSelPct": "92",
        "minPick": "12"
      },
      {
        "draftSelPct": "5",
        "minPick": "14",
        "draftsSelectedIn": "63",
        "maxPick": "79",
        "averagePick": "43.33",
        "id": "14779",
        "rank": "76"
      },
      {
        "id": "17521",
        "draftsSelectedIn": "1018",
        "maxPick": "371",
        "averagePick": "43.34",
        "minPick": "7",
        "draftSelPct": "86",
        "rank": "77"
      },
      {
        "rank": "78",
        "draftSelPct": "91",
        "minPick": "13",
        "maxPick": "532",
        "averagePick": "43.90",
        "draftsSelectedIn": "1079",
        "id": "17652"
      },
      {
        "rank": "79",
        "draftSelPct": "87",
        "minPick": "10",
        "maxPick": "383",
        "averagePick": "43.93",
        "draftsSelectedIn": "1033",
        "id": "17548"
      },
      {
        "rank": "80",
        "draftsSelectedIn": "1015",
        "averagePick": "46.99",
        "maxPick": "441",
        "id": "17529",
        "draftSelPct": "85",
        "minPick": "11"
      },
      {
        "minPick": "18",
        "draftSelPct": "5",
        "id": "15253",
        "averagePick": "47.18",
        "maxPick": "91",
        "draftsSelectedIn": "62",
        "rank": "81"
      },
      {
        "id": "17580",
        "draftsSelectedIn": "476",
        "maxPick": "447",
        "averagePick": "47.66",
        "minPick": "10",
        "draftSelPct": "40",
        "rank": "82"
      },
      {
        "rank": "83",
        "id": "17568",
        "maxPick": "359",
        "averagePick": "47.88",
        "draftsSelectedIn": "462",
        "minPick": "9",
        "draftSelPct": "39"
      },
      {
        "rank": "84",
        "draftsSelectedIn": "996",
        "maxPick": "415",
        "averagePick": "48.60",
        "id": "17519",
        "draftSelPct": "84",
        "minPick": "13"
      },
      {
        "minPick": "18",
        "draftSelPct": "5",
        "id": "15237",
        "averagePick": "49.07",
        "maxPick": "148",
        "draftsSelectedIn": "61",
        "rank": "85"
      },
      {
        "minPick": "27",
        "draftSelPct": "5",
        "id": "17051",
        "maxPick": "80",
        "averagePick": "49.15",
        "draftsSelectedIn": "60",
        "rank": "86"
      },
      {
        "maxPick": "443",
        "averagePick": "49.68",
        "draftsSelectedIn": "415",
        "id": "17562",
        "draftSelPct": "35",
        "minPick": "3",
        "rank": "87"
      },
      {
        "draftsSelectedIn": "454",
        "averagePick": "50.08",
        "maxPick": "482",
        "id": "17575",
        "draftSelPct": "38",
        "minPick": "21",
        "rank": "88"
      },
      {
        "rank": "89",
        "minPick": "11",
        "draftSelPct": "66",
        "id": "17593",
        "draftsSelectedIn": "791",
        "maxPick": "282",
        "averagePick": "51.03"
      },
      {
        "averagePick": "51.57",
        "maxPick": "498",
        "draftsSelectedIn": "425",
        "id": "17623",
        "draftSelPct": "35",
        "minPick": "19",
        "rank": "90"
      },
      {
        "draftSelPct": "64",
        "minPick": "15",
        "maxPick": "290",
        "averagePick": "51.57",
        "draftsSelectedIn": "758",
        "id": "17467",
        "rank": "91"
      },
      {
        "rank": "92",
        "minPick": "12",
        "draftSelPct": "74",
        "id": "17685",
        "averagePick": "51.62",
        "maxPick": "552",
        "draftsSelectedIn": "886"
      },
      {
        "rank": "93",
        "maxPick": "98",
        "averagePick": "51.62",
        "draftsSelectedIn": "61",
        "id": "17045",
        "draftSelPct": "5",
        "minPick": "20"
      },
      {
        "rank": "94",
        "minPick": "8",
        "draftSelPct": "69",
        "id": "17475",
        "maxPick": "459",
        "averagePick": "53.54",
        "draftsSelectedIn": "824"
      },
      {
        "rank": "95",
        "minPick": "16",
        "draftSelPct": "53",
        "id": "17591",
        "averagePick": "54.43",
        "maxPick": "272",
        "draftsSelectedIn": "633"
      },
      {
        "draftSelPct": "32",
        "minPick": "21",
        "draftsSelectedIn": "389",
        "maxPick": "490",
        "averagePick": "54.99",
        "id": "17601",
        "rank": "96"
      },
      {
        "id": "17657",
        "averagePick": "55.81",
        "maxPick": "575",
        "draftsSelectedIn": "670",
        "minPick": "5",
        "draftSelPct": "56",
        "rank": "97"
      },
      {
        "id": "17579",
        "averagePick": "56.20",
        "maxPick": "463",
        "draftsSelectedIn": "325",
        "minPick": "9",
        "draftSelPct": "27",
        "rank": "98"
      },
      {
        "rank": "99",
        "id": "17528",
        "draftsSelectedIn": "663",
        "averagePick": "56.30",
        "maxPick": "477",
        "minPick": "17",
        "draftSelPct": "56"
      },
      {
        "rank": "100",
        "id": "17644",
        "averagePick": "56.38",
        "maxPick": "300",
        "draftsSelectedIn": "461",
        "minPick": "22",
        "draftSelPct": "38"
      },
      {
        "rank": "101",
        "id": "17553",
        "draftsSelectedIn": "334",
        "maxPick": "529",
        "averagePick": "56.46",
        "minPick": "17",
        "draftSelPct": "28"
      },
      {
        "rank": "102",
        "id": "17627",
        "maxPick": "606",
        "averagePick": "56.81",
        "draftsSelectedIn": "538",
        "minPick": "17",
        "draftSelPct": "45"
      },
      {
        "rank": "103",
        "minPick": "5",
        "draftSelPct": "8",
        "id": "15694",
        "draftsSelectedIn": "99",
        "averagePick": "56.98",
        "maxPick": "174"
      },
      {
        "rank": "104",
        "id": "15282",
        "maxPick": "139",
        "averagePick": "57.23",
        "draftsSelectedIn": "60",
        "minPick": "19",
        "draftSelPct": "5"
      },
      {
        "draftSelPct": "54",
        "minPick": "17",
        "averagePick": "57.25",
        "maxPick": "626",
        "draftsSelectedIn": "649",
        "id": "17518",
        "rank": "105"
      },
      {
        "draftsSelectedIn": "489",
        "maxPick": "481",
        "averagePick": "57.64",
        "id": "17654",
        "draftSelPct": "41",
        "minPick": "6",
        "rank": "106"
      },
      {
        "draftsSelectedIn": "523",
        "averagePick": "58.29",
        "maxPick": "422",
        "id": "17549",
        "draftSelPct": "44",
        "minPick": "15",
        "rank": "107"
      },
      {
        "rank": "108",
        "draftSelPct": "28",
        "minPick": "24",
        "draftsSelectedIn": "343",
        "averagePick": "58.74",
        "maxPick": "505",
        "id": "17578"
      },
      {
        "rank": "109",
        "id": "17552",
        "maxPick": "309",
        "averagePick": "59.32",
        "draftsSelectedIn": "321",
        "minPick": "16",
        "draftSelPct": "27"
      },
      {
        "id": "17587",
        "draftsSelectedIn": "320",
        "averagePick": "59.63",
        "maxPick": "476",
        "minPick": "18",
        "draftSelPct": "27",
        "rank": "110"
      },
      {
        "rank": "111",
        "id": "17546",
        "maxPick": "509",
        "averagePick": "59.76",
        "draftsSelectedIn": "440",
        "minPick": "18",
        "draftSelPct": "37"
      },
      {
        "rank": "112",
        "draftSelPct": "47",
        "minPick": "24",
        "maxPick": "543",
        "averagePick": "60.09",
        "draftsSelectedIn": "557",
        "id": "17504"
      },
      {
        "rank": "113",
        "minPick": "19",
        "draftSelPct": "42",
        "id": "17510",
        "averagePick": "60.56",
        "maxPick": "504",
        "draftsSelectedIn": "503"
      },
      {
        "rank": "114",
        "draftsSelectedIn": "236",
        "maxPick": "338",
        "averagePick": "61.29",
        "id": "17569",
        "draftSelPct": "19",
        "minPick": "5"
      },
      {
        "rank": "115",
        "id": "17545",
        "maxPick": "325",
        "averagePick": "61.64",
        "draftsSelectedIn": "275",
        "minPick": "24",
        "draftSelPct": "23"
      },
      {
        "id": "17465",
        "maxPick": "622",
        "averagePick": "62.26",
        "draftsSelectedIn": "360",
        "minPick": "23",
        "draftSelPct": "30",
        "rank": "116"
      },
      {
        "rank": "117",
        "draftSelPct": "14",
        "minPick": "19",
        "draftsSelectedIn": "177",
        "maxPick": "323",
        "averagePick": "62.44",
        "id": "17479"
      },
      {
        "rank": "118",
        "draftSelPct": "24",
        "minPick": "28",
        "averagePick": "62.50",
        "maxPick": "607",
        "draftsSelectedIn": "288",
        "id": "17606"
      },
      {
        "maxPick": "491",
        "averagePick": "63.38",
        "draftsSelectedIn": "225",
        "id": "17555",
        "draftSelPct": "19",
        "minPick": "17",
        "rank": "119"
      },
      {
        "draftSelPct": "29",
        "minPick": "25",
        "draftsSelectedIn": "347",
        "averagePick": "63.54",
        "maxPick": "537",
        "id": "17486",
        "rank": "120"
      },
      {
        "averagePick": "63.61",
        "maxPick": "449",
        "draftsSelectedIn": "257",
        "id": "17583",
        "draftSelPct": "21",
        "minPick": "21",
        "rank": "121"
      },
      {
        "draftsSelectedIn": "394",
        "averagePick": "64.12",
        "maxPick": "526",
        "id": "17542",
        "draftSelPct": "33",
        "minPick": "28",
        "rank": "122"
      },
      {
        "minPick": "32",
        "draftSelPct": "11",
        "id": "17566",
        "averagePick": "64.51",
        "maxPick": "302",
        "draftsSelectedIn": "137",
        "rank": "123"
      },
      {
        "id": "17554",
        "draftsSelectedIn": "264",
        "maxPick": "557",
        "averagePick": "65.01",
        "minPick": "24",
        "draftSelPct": "22",
        "rank": "124"
      },
      {
        "minPick": "25",
        "draftSelPct": "19",
        "id": "17582",
        "maxPick": "105",
        "averagePick": "65.25",
        "draftsSelectedIn": "231",
        "rank": "125"
      },
      {
        "rank": "126",
        "id": "17605",
        "draftsSelectedIn": "329",
        "averagePick": "65.48",
        "maxPick": "621",
        "minPick": "5",
        "draftSelPct": "27"
      },
      {
        "maxPick": "324",
        "averagePick": "65.57",
        "draftsSelectedIn": "272",
        "id": "17706",
        "draftSelPct": "22",
        "minPick": "4",
        "rank": "127"
      },
      {
        "rank": "128",
        "maxPick": "306",
        "averagePick": "66.42",
        "draftsSelectedIn": "205",
        "id": "17620",
        "draftSelPct": "17",
        "minPick": "11"
      },
      {
        "rank": "129",
        "id": "17710",
        "draftsSelectedIn": "91",
        "averagePick": "66.68",
        "maxPick": "207",
        "minPick": "2",
        "draftSelPct": "7"
      },
      {
        "rank": "130",
        "minPick": "15",
        "draftSelPct": "8",
        "id": "15797",
        "draftsSelectedIn": "98",
        "averagePick": "66.73",
        "maxPick": "425"
      },
      {
        "rank": "131",
        "id": "17523",
        "maxPick": "283",
        "averagePick": "66.80",
        "draftsSelectedIn": "205",
        "minPick": "22",
        "draftSelPct": "17"
      },
      {
        "rank": "132",
        "draftSelPct": "18",
        "minPick": "8",
        "averagePick": "67.04",
        "maxPick": "351",
        "draftsSelectedIn": "219",
        "id": "17487"
      },
      {
        "rank": "133",
        "id": "17629",
        "averagePick": "67.07",
        "maxPick": "483",
        "draftsSelectedIn": "249",
        "minPick": "30",
        "draftSelPct": "21"
      },
      {
        "rank": "134",
        "minPick": "14",
        "draftSelPct": "13",
        "id": "17541",
        "maxPick": "145",
        "averagePick": "67.21",
        "draftsSelectedIn": "160"
      },
      {
        "id": "17617",
        "draftsSelectedIn": "222",
        "averagePick": "67.27",
        "maxPick": "577",
        "minPick": "25",
        "draftSelPct": "18",
        "rank": "135"
      },
      {
        "minPick": "26",
        "draftSelPct": "8",
        "id": "17471",
        "maxPick": "318",
        "averagePick": "69.42",
        "draftsSelectedIn": "102",
        "rank": "136"
      },
      {
        "rank": "137",
        "draftsSelectedIn": "179",
        "averagePick": "70.63",
        "maxPick": "326",
        "id": "17584",
        "draftSelPct": "15",
        "minPick": "24"
      },
      {
        "rank": "138",
        "minPick": "27",
        "draftSelPct": "17",
        "id": "17588",
        "maxPick": "584",
        "averagePick": "70.99",
        "draftsSelectedIn": "202"
      },
      {
        "draftSelPct": "14",
        "minPick": "19",
        "maxPick": "450",
        "averagePick": "71.14",
        "draftsSelectedIn": "177",
        "id": "17668",
        "rank": "139"
      },
      {
        "minPick": "37",
        "draftSelPct": "12",
        "id": "17709",
        "draftsSelectedIn": "145",
        "averagePick": "71.23",
        "maxPick": "193",
        "rank": "140"
      },
      {
        "draftSelPct": "10",
        "minPick": "41",
        "draftsSelectedIn": "130",
        "averagePick": "71.39",
        "maxPick": "200",
        "id": "17655",
        "rank": "141"
      },
      {
        "draftsSelectedIn": "196",
        "averagePick": "71.52",
        "maxPick": "366",
        "id": "17573",
        "draftSelPct": "16",
        "minPick": "20",
        "rank": "142"
      },
      {
        "rank": "143",
        "draftsSelectedIn": "156",
        "averagePick": "72.36",
        "maxPick": "601",
        "id": "17480",
        "draftSelPct": "13",
        "minPick": "12"
      },
      {
        "rank": "144",
        "draftSelPct": "16",
        "minPick": "17",
        "maxPick": "608",
        "averagePick": "73.18",
        "draftsSelectedIn": "194",
        "id": "17594"
      },
      {
        "rank": "145",
        "draftSelPct": "13",
        "minPick": "23",
        "draftsSelectedIn": "160",
        "maxPick": "507",
        "averagePick": "73.78",
        "id": "17526"
      },
      {
        "rank": "146",
        "draftSelPct": "14",
        "minPick": "14",
        "draftsSelectedIn": "173",
        "averagePick": "74.63",
        "maxPick": "562",
        "id": "17590"
      },
      {
        "rank": "147",
        "id": "17665",
        "maxPick": "160",
        "averagePick": "75.19",
        "draftsSelectedIn": "151",
        "minPick": "18",
        "draftSelPct": "12"
      },
      {
        "rank": "148",
        "minPick": "38",
        "draftSelPct": "7",
        "id": "17648",
        "maxPick": "179",
        "averagePick": "75.55",
        "draftsSelectedIn": "88"
      },
      {
        "minPick": "25",
        "draftSelPct": "14",
        "id": "17667",
        "averagePick": "75.75",
        "maxPick": "122",
        "draftsSelectedIn": "166",
        "rank": "149"
      },
      {
        "id": "17628",
        "draftsSelectedIn": "141",
        "averagePick": "75.76",
        "maxPick": "124",
        "minPick": "26",
        "draftSelPct": "11",
        "rank": "150"
      },
      {
        "draftSelPct": "7",
        "minPick": "23",
        "maxPick": "150",
        "averagePick": "75.81",
        "draftsSelectedIn": "93",
        "id": "17561",
        "rank": "151"
      },
      {
        "rank": "152",
        "draftsSelectedIn": "128",
        "averagePick": "76.20",
        "maxPick": "519",
        "id": "17647",
        "draftSelPct": "10",
        "minPick": "33"
      },
      {
        "draftSelPct": "9",
        "minPick": "15",
        "maxPick": "600",
        "averagePick": "77.18",
        "draftsSelectedIn": "107",
        "id": "17527",
        "rank": "153"
      },
      {
        "rank": "154",
        "draftSelPct": "11",
        "minPick": "43",
        "draftsSelectedIn": "132",
        "averagePick": "80.74",
        "maxPick": "122",
        "id": "17621"
      },
      {
        "rank": "155",
        "draftSelPct": "9",
        "minPick": "22",
        "draftsSelectedIn": "110",
        "maxPick": "144",
        "averagePick": "81.16",
        "id": "17619"
      },
      {
        "rank": "156",
        "id": "17608",
        "draftsSelectedIn": "128",
        "maxPick": "120",
        "averagePick": "83.17",
        "minPick": "41",
        "draftSelPct": "10"
      },
      {
        "draftSelPct": "9",
        "minPick": "27",
        "maxPick": "612",
        "averagePick": "85.03",
        "draftsSelectedIn": "108",
        "id": "17572",
        "rank": "157"
      },
      {
        "rank": "158",
        "averagePick": "86.23",
        "maxPick": "614",
        "draftsSelectedIn": "130",
        "id": "17645",
        "draftSelPct": "10",
        "minPick": "14"
      },
      {
        "rank": "159",
        "id": "17700",
        "maxPick": "138",
        "averagePick": "86.76",
        "draftsSelectedIn": "94",
        "minPick": "38",
        "draftSelPct": "7"
      },
      {
        "id": "17574",
        "draftsSelectedIn": "94",
        "averagePick": "87.94",
        "maxPick": "514",
        "minPick": "29",
        "draftSelPct": "7",
        "rank": "160"
      },
      {
        "minPick": "38",
        "draftSelPct": "5",
        "id": "17570",
        "averagePick": "88.60",
        "maxPick": "148",
        "draftsSelectedIn": "67",
        "rank": "161"
      },
      {
        "id": "17634",
        "draftsSelectedIn": "88",
        "averagePick": "88.67",
        "maxPick": "156",
        "minPick": "40",
        "draftSelPct": "7",
        "rank": "162"
      },
      {
        "rank": "163",
        "minPick": "29",
        "draftSelPct": "7",
        "id": "17585",
        "draftsSelectedIn": "86",
        "averagePick": "89.74",
        "maxPick": "628"
      },
      {
        "rank": "164",
        "draftSelPct": "5",
        "minPick": "46",
        "draftsSelectedIn": "63",
        "maxPick": "142",
        "averagePick": "91.22",
        "id": "17592"
      },
      {
        "rank": "165",
        "draftSelPct": "8",
        "minPick": "43",
        "draftsSelectedIn": "97",
        "maxPick": "623",
        "averagePick": "93.93",
        "id": "17646"
      },
      {
        "id": "17616",
        "draftsSelectedIn": "61",
        "averagePick": "94.15",
        "maxPick": "141",
        "minPick": "38",
        "draftSelPct": "5",
        "rank": "166"
      },
      {
        "draftSelPct": "6",
        "minPick": "15",
        "maxPick": "127",
        "averagePick": "94.42",
        "draftsSelectedIn": "76",
        "id": "17597",
        "rank": "167"
      },
      {
        "rank": "168",
        "draftsSelectedIn": "64",
        "averagePick": "98.98",
        "maxPick": "572",
        "id": "17596",
        "draftSelPct": "5",
        "minPick": "52"
      }
    ],
    "totalDrafts": "1183"
  }
}