{
  "version": "1.0",
  "encoding": "utf-8",
  "adp": {
    "totalDrafts": "644",
    "player": [
      {
        "draftsSelectedIn": "636",
        "maxPick": "60",
        "draftSelPct": "98",
        "averagePick": "2.24",
        "minPick": "1",
        "id": "17472",
        "rank": "1"
      },
      {
        "rank": "2",
        "id": "17497",
        "minPick": "1",
        "averagePick": "4.99",
        "draftSelPct": "97",
        "maxPick": "119",
        "draftsSelectedIn": "630"
      },
      {
        "maxPick": "133",
        "draftsSelectedIn": "690",
        "draftSelPct": "107",
        "id": "17473",
        "minPick": "1",
        "averagePick": "7.26",
        "rank": "3"
      },
      {
        "draftsSelectedIn": "638",
        "maxPick": "142",
        "draftSelPct": "99",
        "averagePick": "7.65",
        "id": "17498",
        "minPick": "1",
        "rank": "4"
      },
      {
        "draftSelPct": "100",
        "draftsSelectedIn": "646",
        "maxPick": "151",
        "rank": "5",
        "averagePick": "8.48",
        "minPick": "1",
        "id": "17499"
      },
      {
        "averagePick": "8.81",
        "minPick": "1",
        "id": "17462",
        "rank": "6",
        "draftsSelectedIn": "663",
        "maxPick": "299",
        "draftSelPct": "102"
      },
      {
        "minPick": "2",
        "id": "17557",
        "averagePick": "10.78",
        "rank": "7",
        "maxPick": "100",
        "draftsSelectedIn": "283",
        "draftSelPct": "43"
      },
      {
        "rank": "8",
        "id": "17543",
        "minPick": "1",
        "averagePick": "10.88",
        "draftSelPct": "105",
        "maxPick": "151",
        "draftsSelectedIn": "677"
      },
      {
        "draftSelPct": "102",
        "maxPick": "248",
        "draftsSelectedIn": "659",
        "rank": "9",
        "minPick": "2",
        "id": "17501",
        "averagePick": "11.79"
      },
      {
        "rank": "10",
        "minPick": "1",
        "id": "17544",
        "averagePick": "15.16",
        "draftSelPct": "103",
        "maxPick": "282",
        "draftsSelectedIn": "668"
      },
      {
        "maxPick": "202",
        "draftsSelectedIn": "679",
        "draftSelPct": "105",
        "id": "17502",
        "minPick": "2",
        "averagePick": "15.43",
        "rank": "11"
      },
      {
        "rank": "12",
        "minPick": "1",
        "id": "17558",
        "averagePick": "16.55",
        "draftSelPct": "43",
        "maxPick": "146",
        "draftsSelectedIn": "278"
      },
      {
        "rank": "13",
        "averagePick": "17.38",
        "id": "17556",
        "minPick": "2",
        "draftSelPct": "44",
        "draftsSelectedIn": "285",
        "maxPick": "159"
      },
      {
        "rank": "14",
        "averagePick": "19.33",
        "id": "17477",
        "minPick": "2",
        "draftSelPct": "100",
        "draftsSelectedIn": "649",
        "maxPick": "398"
      },
      {
        "averagePick": "19.33",
        "minPick": "4",
        "id": "17500",
        "rank": "15",
        "draftsSelectedIn": "653",
        "maxPick": "399",
        "draftSelPct": "101"
      },
      {
        "draftSelPct": "100",
        "draftsSelectedIn": "649",
        "maxPick": "257",
        "rank": "16",
        "averagePick": "21.62",
        "id": "17512",
        "minPick": "6"
      },
      {
        "rank": "17",
        "averagePick": "22.17",
        "id": "17463",
        "minPick": "1",
        "draftSelPct": "100",
        "draftsSelectedIn": "644",
        "maxPick": "503"
      },
      {
        "draftSelPct": "43",
        "maxPick": "179",
        "draftsSelectedIn": "281",
        "rank": "18",
        "minPick": "3",
        "id": "17551",
        "averagePick": "22.53"
      },
      {
        "draftSelPct": "43",
        "maxPick": "167",
        "draftsSelectedIn": "278",
        "rank": "19",
        "id": "17563",
        "minPick": "2",
        "averagePick": "23.02"
      },
      {
        "averagePick": "24.30",
        "minPick": "3",
        "id": "17506",
        "rank": "20",
        "draftsSelectedIn": "676",
        "maxPick": "315",
        "draftSelPct": "104"
      },
      {
        "draftSelPct": "104",
        "draftsSelectedIn": "673",
        "maxPick": "347",
        "rank": "21",
        "averagePick": "24.45",
        "id": "17503",
        "minPick": "4"
      },
      {
        "minPick": "4",
        "id": "17586",
        "averagePick": "24.51",
        "rank": "22",
        "maxPick": "395",
        "draftsSelectedIn": "285",
        "draftSelPct": "44"
      },
      {
        "rank": "23",
        "id": "17476",
        "minPick": "4",
        "averagePick": "24.73",
        "draftSelPct": "96",
        "maxPick": "459",
        "draftsSelectedIn": "622"
      },
      {
        "rank": "24",
        "averagePick": "25.50",
        "id": "17550",
        "minPick": "6",
        "draftSelPct": "42",
        "draftsSelectedIn": "276",
        "maxPick": "168"
      },
      {
        "draftsSelectedIn": "681",
        "maxPick": "428",
        "draftSelPct": "105",
        "averagePick": "26.82",
        "id": "17514",
        "minPick": "6",
        "rank": "25"
      },
      {
        "draftSelPct": "103",
        "draftsSelectedIn": "669",
        "maxPick": "457",
        "rank": "26",
        "averagePick": "29.38",
        "id": "17520",
        "minPick": "4"
      },
      {
        "maxPick": "452",
        "draftsSelectedIn": "674",
        "draftSelPct": "104",
        "id": "17474",
        "minPick": "5",
        "averagePick": "30.47",
        "rank": "27"
      },
      {
        "maxPick": "199",
        "draftsSelectedIn": "279",
        "draftSelPct": "43",
        "minPick": "5",
        "id": "17576",
        "averagePick": "30.96",
        "rank": "28"
      },
      {
        "rank": "29",
        "minPick": "5",
        "id": "17482",
        "averagePick": "31.05",
        "draftSelPct": "103",
        "maxPick": "377",
        "draftsSelectedIn": "667"
      },
      {
        "maxPick": "458",
        "draftsSelectedIn": "661",
        "draftSelPct": "102",
        "id": "17509",
        "minPick": "5",
        "averagePick": "32.08",
        "rank": "30"
      },
      {
        "minPick": "8",
        "id": "17560",
        "averagePick": "32.34",
        "rank": "31",
        "maxPick": "248",
        "draftsSelectedIn": "276",
        "draftSelPct": "42"
      },
      {
        "draftsSelectedIn": "618",
        "maxPick": "293",
        "draftSelPct": "95",
        "averagePick": "32.74",
        "id": "17507",
        "minPick": "12",
        "rank": "32"
      },
      {
        "id": "17511",
        "minPick": "6",
        "averagePick": "33.69",
        "rank": "33",
        "maxPick": "464",
        "draftsSelectedIn": "661",
        "draftSelPct": "102"
      },
      {
        "maxPick": "433",
        "draftsSelectedIn": "672",
        "draftSelPct": "104",
        "minPick": "9",
        "id": "17485",
        "averagePick": "34.35",
        "rank": "34"
      },
      {
        "averagePick": "34.51",
        "id": "17478",
        "minPick": "4",
        "rank": "35",
        "draftsSelectedIn": "636",
        "maxPick": "471",
        "draftSelPct": "98"
      },
      {
        "averagePick": "34.73",
        "id": "17589",
        "minPick": "11",
        "rank": "36",
        "draftsSelectedIn": "273",
        "maxPick": "379",
        "draftSelPct": "42"
      },
      {
        "draftSelPct": "100",
        "maxPick": "289",
        "draftsSelectedIn": "646",
        "rank": "37",
        "minPick": "8",
        "id": "17547",
        "averagePick": "36.08"
      },
      {
        "draftsSelectedIn": "594",
        "maxPick": "526",
        "draftSelPct": "92",
        "averagePick": "37.30",
        "id": "17466",
        "minPick": "6",
        "rank": "38"
      },
      {
        "draftSelPct": "94",
        "draftsSelectedIn": "611",
        "maxPick": "272",
        "rank": "39",
        "averagePick": "38.49",
        "minPick": "9",
        "id": "17567"
      },
      {
        "averagePick": "38.77",
        "id": "17607",
        "minPick": "8",
        "rank": "40",
        "draftsSelectedIn": "635",
        "maxPick": "365",
        "draftSelPct": "98"
      },
      {
        "draftSelPct": "40",
        "draftsSelectedIn": "262",
        "maxPick": "415",
        "rank": "41",
        "averagePick": "40.05",
        "id": "17571",
        "minPick": "12"
      },
      {
        "rank": "42",
        "minPick": "12",
        "id": "17508",
        "averagePick": "40.15",
        "draftSelPct": "102",
        "maxPick": "531",
        "draftsSelectedIn": "659"
      },
      {
        "draftSelPct": "102",
        "draftsSelectedIn": "660",
        "maxPick": "500",
        "rank": "43",
        "averagePick": "40.98",
        "id": "17481",
        "minPick": "10"
      },
      {
        "averagePick": "41.38",
        "minPick": "5",
        "id": "17505",
        "rank": "44",
        "draftsSelectedIn": "639",
        "maxPick": "445",
        "draftSelPct": "99"
      },
      {
        "rank": "45",
        "minPick": "13",
        "id": "17517",
        "averagePick": "42.89",
        "draftSelPct": "96",
        "maxPick": "262",
        "draftsSelectedIn": "624"
      },
      {
        "draftSelPct": "31",
        "maxPick": "214",
        "draftsSelectedIn": "203",
        "rank": "46",
        "minPick": "11",
        "id": "17722",
        "averagePick": "44.34"
      },
      {
        "rank": "47",
        "averagePick": "44.38",
        "minPick": "18",
        "id": "17652",
        "draftSelPct": "97",
        "draftsSelectedIn": "625",
        "maxPick": "303"
      },
      {
        "draftSelPct": "83",
        "draftsSelectedIn": "536",
        "maxPick": "547",
        "rank": "48",
        "averagePick": "44.87",
        "id": "17468",
        "minPick": "15"
      },
      {
        "rank": "49",
        "averagePick": "45.11",
        "minPick": "6",
        "id": "17521",
        "draftSelPct": "90",
        "draftsSelectedIn": "581",
        "maxPick": "410"
      },
      {
        "draftSelPct": "92",
        "draftsSelectedIn": "594",
        "maxPick": "275",
        "rank": "50",
        "averagePick": "45.55",
        "id": "17599",
        "minPick": "6"
      },
      {
        "draftSelPct": "89",
        "maxPick": "462",
        "draftsSelectedIn": "577",
        "rank": "51",
        "id": "17548",
        "minPick": "9",
        "averagePick": "46.12"
      },
      {
        "maxPick": "177",
        "draftsSelectedIn": "220",
        "draftSelPct": "34",
        "id": "17562",
        "minPick": "11",
        "averagePick": "46.52",
        "rank": "52"
      },
      {
        "minPick": "16",
        "id": "17580",
        "averagePick": "47.49",
        "rank": "53",
        "maxPick": "407",
        "draftsSelectedIn": "251",
        "draftSelPct": "38"
      },
      {
        "draftsSelectedIn": "233",
        "maxPick": "436",
        "draftSelPct": "36",
        "averagePick": "48.12",
        "id": "17568",
        "minPick": "17",
        "rank": "54"
      },
      {
        "draftsSelectedIn": "223",
        "maxPick": "456",
        "draftSelPct": "34",
        "averagePick": "49.82",
        "minPick": "18",
        "id": "17623",
        "rank": "55"
      },
      {
        "rank": "56",
        "averagePick": "50.17",
        "id": "17519",
        "minPick": "18",
        "draftSelPct": "84",
        "draftsSelectedIn": "543",
        "maxPick": "277"
      },
      {
        "minPick": "13",
        "id": "17575",
        "averagePick": "50.94",
        "rank": "57",
        "maxPick": "290",
        "draftsSelectedIn": "220",
        "draftSelPct": "34"
      },
      {
        "maxPick": "426",
        "draftsSelectedIn": "559",
        "draftSelPct": "86",
        "minPick": "17",
        "id": "17529",
        "averagePick": "51.43",
        "rank": "58"
      },
      {
        "draftsSelectedIn": "410",
        "maxPick": "491",
        "draftSelPct": "63",
        "averagePick": "52.46",
        "id": "17593",
        "minPick": "15",
        "rank": "59"
      },
      {
        "draftSelPct": "67",
        "maxPick": "309",
        "draftsSelectedIn": "432",
        "rank": "60",
        "minPick": "13",
        "id": "17467",
        "averagePick": "52.54"
      },
      {
        "maxPick": "400",
        "draftsSelectedIn": "205",
        "draftSelPct": "31",
        "minPick": "9",
        "id": "17629",
        "averagePick": "53.20",
        "rank": "61"
      },
      {
        "rank": "62",
        "minPick": "16",
        "id": "17685",
        "averagePick": "54.24",
        "draftSelPct": "75",
        "maxPick": "306",
        "draftsSelectedIn": "489"
      },
      {
        "rank": "63",
        "id": "17601",
        "minPick": "14",
        "averagePick": "55.00",
        "draftSelPct": "35",
        "maxPick": "480",
        "draftsSelectedIn": "228"
      },
      {
        "rank": "64",
        "averagePick": "55.22",
        "id": "17579",
        "minPick": "15",
        "draftSelPct": "27",
        "draftsSelectedIn": "179",
        "maxPick": "215"
      },
      {
        "draftSelPct": "73",
        "maxPick": "340",
        "draftsSelectedIn": "475",
        "rank": "65",
        "id": "17475",
        "minPick": "14",
        "averagePick": "55.85"
      },
      {
        "minPick": "14",
        "id": "17553",
        "averagePick": "57.28",
        "rank": "66",
        "maxPick": "194",
        "draftsSelectedIn": "189",
        "draftSelPct": "29"
      },
      {
        "maxPick": "289",
        "draftsSelectedIn": "299",
        "draftSelPct": "46",
        "minPick": "15",
        "id": "17627",
        "averagePick": "57.33",
        "rank": "67"
      },
      {
        "maxPick": "286",
        "draftsSelectedIn": "403",
        "draftSelPct": "62",
        "id": "17518",
        "minPick": "16",
        "averagePick": "57.48",
        "rank": "68"
      },
      {
        "draftSelPct": "16",
        "draftsSelectedIn": "106",
        "maxPick": "113",
        "rank": "69",
        "averagePick": "57.94",
        "id": "17668",
        "minPick": "21"
      },
      {
        "draftsSelectedIn": "267",
        "maxPick": "381",
        "draftSelPct": "41",
        "averagePick": "58.55",
        "minPick": "18",
        "id": "17549",
        "rank": "70"
      },
      {
        "rank": "71",
        "minPick": "15",
        "id": "17657",
        "averagePick": "58.82",
        "draftSelPct": "44",
        "maxPick": "337",
        "draftsSelectedIn": "287"
      },
      {
        "rank": "72",
        "id": "17591",
        "minPick": "15",
        "averagePick": "59.07",
        "draftSelPct": "52",
        "maxPick": "357",
        "draftsSelectedIn": "338"
      },
      {
        "id": "17654",
        "minPick": "2",
        "averagePick": "59.59",
        "rank": "73",
        "maxPick": "305",
        "draftsSelectedIn": "198",
        "draftSelPct": "30"
      },
      {
        "averagePick": "60.16",
        "minPick": "22",
        "id": "17644",
        "rank": "74",
        "draftsSelectedIn": "256",
        "maxPick": "356",
        "draftSelPct": "39"
      },
      {
        "averagePick": "60.18",
        "minPick": "27",
        "id": "17528",
        "rank": "75",
        "draftsSelectedIn": "370",
        "maxPick": "536",
        "draftSelPct": "57"
      },
      {
        "maxPick": "447",
        "draftsSelectedIn": "171",
        "draftSelPct": "26",
        "id": "17578",
        "minPick": "21",
        "averagePick": "60.47",
        "rank": "76"
      },
      {
        "maxPick": "485",
        "draftsSelectedIn": "182",
        "draftSelPct": "28",
        "minPick": "16",
        "id": "17587",
        "averagePick": "60.48",
        "rank": "77"
      },
      {
        "rank": "78",
        "minPick": "17",
        "id": "17552",
        "averagePick": "60.79",
        "draftSelPct": "28",
        "maxPick": "422",
        "draftsSelectedIn": "182"
      },
      {
        "id": "15694",
        "minPick": "2",
        "averagePick": "61.23",
        "rank": "79",
        "maxPick": "200",
        "draftsSelectedIn": "62",
        "draftSelPct": "9"
      },
      {
        "rank": "80",
        "averagePick": "63.02",
        "minPick": "36",
        "id": "17510",
        "draftSelPct": "40",
        "draftsSelectedIn": "262",
        "maxPick": "352"
      },
      {
        "rank": "81",
        "id": "17583",
        "minPick": "19",
        "averagePick": "63.05",
        "draftSelPct": "22",
        "maxPick": "487",
        "draftsSelectedIn": "145"
      },
      {
        "averagePick": "63.99",
        "id": "17606",
        "minPick": "29",
        "rank": "82",
        "draftsSelectedIn": "151",
        "maxPick": "516",
        "draftSelPct": "23"
      },
      {
        "rank": "83",
        "averagePick": "64.60",
        "id": "17465",
        "minPick": "25",
        "draftSelPct": "21",
        "draftsSelectedIn": "139",
        "maxPick": "336"
      },
      {
        "rank": "84",
        "averagePick": "64.70",
        "id": "17504",
        "minPick": "18",
        "draftSelPct": "42",
        "draftsSelectedIn": "272",
        "maxPick": "460"
      },
      {
        "maxPick": "343",
        "draftsSelectedIn": "159",
        "draftSelPct": "24",
        "id": "17545",
        "minPick": "29",
        "averagePick": "64.76",
        "rank": "85"
      },
      {
        "draftSelPct": "33",
        "draftsSelectedIn": "216",
        "maxPick": "340",
        "rank": "86",
        "averagePick": "64.92",
        "id": "17546",
        "minPick": "25"
      },
      {
        "rank": "87",
        "averagePick": "65.09",
        "id": "17486",
        "minPick": "15",
        "draftSelPct": "28",
        "draftsSelectedIn": "181",
        "maxPick": "542"
      },
      {
        "maxPick": "513",
        "draftsSelectedIn": "221",
        "draftSelPct": "34",
        "minPick": "14",
        "id": "17542",
        "averagePick": "65.36",
        "rank": "88"
      },
      {
        "draftSelPct": "18",
        "maxPick": "341",
        "draftsSelectedIn": "116",
        "rank": "89",
        "id": "17487",
        "minPick": "10",
        "averagePick": "66.32"
      },
      {
        "rank": "90",
        "id": "17655",
        "minPick": "37",
        "averagePick": "66.83",
        "draftSelPct": "11",
        "maxPick": "312",
        "draftsSelectedIn": "77"
      },
      {
        "maxPick": "359",
        "draftsSelectedIn": "204",
        "draftSelPct": "31",
        "minPick": "19",
        "id": "17605",
        "averagePick": "66.84",
        "rank": "91"
      },
      {
        "draftSelPct": "17",
        "draftsSelectedIn": "112",
        "maxPick": "227",
        "rank": "92",
        "averagePick": "67.25",
        "minPick": "24",
        "id": "17573"
      },
      {
        "draftsSelectedIn": "102",
        "maxPick": "206",
        "draftSelPct": "15",
        "averagePick": "67.61",
        "id": "17582",
        "minPick": "18",
        "rank": "93"
      },
      {
        "rank": "94",
        "averagePick": "67.98",
        "id": "17554",
        "minPick": "33",
        "draftSelPct": "21",
        "draftsSelectedIn": "137",
        "maxPick": "444"
      },
      {
        "rank": "95",
        "id": "17569",
        "minPick": "17",
        "averagePick": "68.13",
        "draftSelPct": "17",
        "maxPick": "402",
        "draftsSelectedIn": "113"
      },
      {
        "draftSelPct": "15",
        "maxPick": "312",
        "draftsSelectedIn": "101",
        "rank": "96",
        "id": "16387",
        "minPick": "25",
        "averagePick": "68.19"
      },
      {
        "rank": "97",
        "averagePick": "68.36",
        "minPick": "41",
        "id": "17526",
        "draftSelPct": "12",
        "draftsSelectedIn": "83",
        "maxPick": "142"
      },
      {
        "rank": "98",
        "averagePick": "68.60",
        "minPick": "18",
        "id": "17555",
        "draftSelPct": "19",
        "draftsSelectedIn": "128",
        "maxPick": "450"
      },
      {
        "averagePick": "68.79",
        "minPick": "40",
        "id": "17710",
        "rank": "99",
        "draftsSelectedIn": "67",
        "maxPick": "365",
        "draftSelPct": "10"
      },
      {
        "draftSelPct": "16",
        "draftsSelectedIn": "106",
        "maxPick": "263",
        "rank": "100",
        "averagePick": "69.51",
        "minPick": "27",
        "id": "17590"
      },
      {
        "maxPick": "295",
        "draftsSelectedIn": "78",
        "draftSelPct": "12",
        "minPick": "31",
        "id": "17523",
        "averagePick": "69.96",
        "rank": "101"
      },
      {
        "draftSelPct": "18",
        "maxPick": "538",
        "draftsSelectedIn": "121",
        "rank": "102",
        "minPick": "26",
        "id": "17588",
        "averagePick": "71.61"
      },
      {
        "draftsSelectedIn": "117",
        "maxPick": "540",
        "draftSelPct": "18",
        "averagePick": "72.53",
        "id": "17617",
        "minPick": "28",
        "rank": "103"
      },
      {
        "rank": "104",
        "minPick": "31",
        "id": "17706",
        "averagePick": "73.20",
        "draftSelPct": "18",
        "maxPick": "390",
        "draftsSelectedIn": "119"
      },
      {
        "rank": "105",
        "averagePick": "73.28",
        "minPick": "41",
        "id": "17645",
        "draftSelPct": "10",
        "draftsSelectedIn": "68",
        "maxPick": "120"
      },
      {
        "rank": "106",
        "averagePick": "73.65",
        "id": "17594",
        "minPick": "24",
        "draftSelPct": "17",
        "draftsSelectedIn": "115",
        "maxPick": "548"
      },
      {
        "draftSelPct": "10",
        "draftsSelectedIn": "66",
        "maxPick": "329",
        "rank": "107",
        "averagePick": "74.17",
        "minPick": "36",
        "id": "17709"
      },
      {
        "draftSelPct": "6",
        "draftsSelectedIn": "44",
        "maxPick": "130",
        "rank": "108",
        "averagePick": "74.27",
        "minPick": "12",
        "id": "17561"
      },
      {
        "maxPick": "453",
        "draftsSelectedIn": "102",
        "draftSelPct": "15",
        "id": "17620",
        "minPick": "9",
        "averagePick": "74.71",
        "rank": "109"
      },
      {
        "draftsSelectedIn": "56",
        "maxPick": "334",
        "draftSelPct": "8",
        "averagePick": "74.91",
        "id": "17566",
        "minPick": "35",
        "rank": "110"
      },
      {
        "draftsSelectedIn": "74",
        "maxPick": "119",
        "draftSelPct": "11",
        "averagePick": "75.09",
        "id": "17665",
        "minPick": "25",
        "rank": "111"
      },
      {
        "averagePick": "75.43",
        "minPick": "29",
        "id": "17667",
        "rank": "112",
        "draftsSelectedIn": "56",
        "maxPick": "126",
        "draftSelPct": "8"
      },
      {
        "draftSelPct": "14",
        "draftsSelectedIn": "91",
        "maxPick": "366",
        "rank": "113",
        "averagePick": "75.69",
        "minPick": "16",
        "id": "15797"
      },
      {
        "averagePick": "77.21",
        "minPick": "23",
        "id": "17584",
        "rank": "114",
        "draftsSelectedIn": "101",
        "maxPick": "545",
        "draftSelPct": "15"
      },
      {
        "draftsSelectedIn": "77",
        "maxPick": "476",
        "draftSelPct": "11",
        "averagePick": "77.87",
        "id": "17541",
        "minPick": "22",
        "rank": "115"
      },
      {
        "draftSelPct": "9",
        "draftsSelectedIn": "61",
        "maxPick": "125",
        "rank": "116",
        "averagePick": "78.74",
        "minPick": "35",
        "id": "17619"
      },
      {
        "rank": "117",
        "id": "17572",
        "minPick": "39",
        "averagePick": "80.28",
        "draftSelPct": "8",
        "maxPick": "359",
        "draftsSelectedIn": "57"
      },
      {
        "minPick": "32",
        "id": "17480",
        "averagePick": "80.84",
        "rank": "118",
        "maxPick": "356",
        "draftsSelectedIn": "68",
        "draftSelPct": "10"
      },
      {
        "draftSelPct": "8",
        "maxPick": "124",
        "draftsSelectedIn": "57",
        "rank": "119",
        "minPick": "41",
        "id": "17700",
        "averagePick": "82.88"
      },
      {
        "rank": "120",
        "minPick": "42",
        "id": "17527",
        "averagePick": "83.49",
        "draftSelPct": "6",
        "maxPick": "386",
        "draftsSelectedIn": "43"
      },
      {
        "rank": "121",
        "averagePick": "83.86",
        "id": "17608",
        "minPick": "35",
        "draftSelPct": "7",
        "draftsSelectedIn": "51",
        "maxPick": "322"
      },
      {
        "rank": "122",
        "id": "17574",
        "minPick": "38",
        "averagePick": "84.11",
        "draftSelPct": "8",
        "maxPick": "276",
        "draftsSelectedIn": "53"
      },
      {
        "maxPick": "371",
        "draftsSelectedIn": "38",
        "draftSelPct": "5",
        "minPick": "38",
        "id": "17471",
        "averagePick": "86.95",
        "rank": "123"
      },
      {
        "draftSelPct": "9",
        "maxPick": "539",
        "draftsSelectedIn": "61",
        "rank": "124",
        "id": "17621",
        "minPick": "48",
        "averagePick": "89.10"
      },
      {
        "minPick": "41",
        "id": "17628",
        "averagePick": "89.29",
        "rank": "125",
        "maxPick": "541",
        "draftsSelectedIn": "59",
        "draftSelPct": "9"
      },
      {
        "draftsSelectedIn": "40",
        "maxPick": "379",
        "draftSelPct": "6",
        "averagePick": "89.42",
        "minPick": "21",
        "id": "17648",
        "rank": "126"
      },
      {
        "id": "17592",
        "minPick": "42",
        "averagePick": "90.16",
        "rank": "127",
        "maxPick": "322",
        "draftsSelectedIn": "45",
        "draftSelPct": "6"
      },
      {
        "maxPick": "514",
        "draftsSelectedIn": "48",
        "draftSelPct": "7",
        "id": "17646",
        "minPick": "41",
        "averagePick": "90.23",
        "rank": "128"
      },
      {
        "rank": "129",
        "minPick": "63",
        "id": "17636",
        "averagePick": "95.31",
        "draftSelPct": "5",
        "maxPick": "147",
        "draftsSelectedIn": "36"
      },
      {
        "rank": "130",
        "averagePick": "95.52",
        "minPick": "32",
        "id": "15738",
        "draftSelPct": "5",
        "draftsSelectedIn": "33",
        "maxPick": "310"
      },
      {
        "draftSelPct": "6",
        "maxPick": "528",
        "draftsSelectedIn": "43",
        "rank": "131",
        "id": "17634",
        "minPick": "50",
        "averagePick": "95.53"
      },
      {
        "rank": "132",
        "averagePick": "102.41",
        "minPick": "41",
        "id": "17585",
        "draftSelPct": "5",
        "draftsSelectedIn": "37",
        "maxPick": "554"
      },
      {
        "id": "15786",
        "minPick": "23",
        "averagePick": "106.67",
        "rank": "133",
        "maxPick": "233",
        "draftsSelectedIn": "36",
        "draftSelPct": "5"
      },
      {
        "draftSelPct": "5",
        "draftsSelectedIn": "37",
        "maxPick": "278",
        "rank": "134",
        "averagePick": "110.32",
        "minPick": "19",
        "id": "15889"
      },
      {
        "rank": "135",
        "id": "16036",
        "minPick": "12",
        "averagePick": "111.97",
        "draftSelPct": "5",
        "maxPick": "336",
        "draftsSelectedIn": "36"
      },
      {
        "draftSelPct": "6",
        "draftsSelectedIn": "40",
        "maxPick": "544",
        "rank": "136",
        "averagePick": "117.30",
        "id": "13113",
        "minPick": "21"
      }
    ],
    "totalPicks": "525",
    "timestamp": "1781630363"
  }
}