{
  "version": "1.0",
  "transactions": {
    "transaction": [
      {
        "timestamp": "1783960218",
        "transaction": "|16169,15255,17048,15972,16165,14860,",
        "type": "FREE_AGENT",
        "franchise": "0021"
      },
      {
        "timestamp": "1783954491",
        "transaction": "|12186,",
        "franchise": "0004",
        "type": "FREE_AGENT"
      },
      {
        "timestamp": "1783954485",
        "type": "FREE_AGENT",
        "franchise": "0005",
        "transaction": "|0532,"
      },
      {
        "transaction": "|11936,",
        "franchise": "0005",
        "type": "FREE_AGENT",
        "timestamp": "1783954484"
      },
      {
        "timestamp": "1783954483",
        "type": "FREE_AGENT",
        "franchise": "0005",
        "transaction": "|16269,"
      },
      {
        "transaction": "|17099,",
        "type": "FREE_AGENT",
        "franchise": "0005",
        "timestamp": "1783954483"
      },
      {
        "timestamp": "1783954482",
        "type": "FREE_AGENT",
        "franchise": "0005",
        "transaction": "|16626,"
      },
      {
        "transaction": "|14840,",
        "franchise": "0005",
        "type": "FREE_AGENT",
        "timestamp": "1783954481"
      },
      {
        "franchise": "0005",
        "type": "FREE_AGENT",
        "transaction": "|16610,",
        "timestamp": "1783954480"
      },
      {
        "timestamp": "1783954479",
        "transaction": "|15716,",
        "type": "FREE_AGENT",
        "franchise": "0005"
      },
      {
        "timestamp": "1783954479",
        "transaction": "|16171,",
        "franchise": "0005",
        "type": "FREE_AGENT"
      },
      {
        "timestamp": "1783954478",
        "type": "FREE_AGENT",
        "franchise": "0005",
        "transaction": "|15727,"
      },
      {
        "timestamp": "1783954477",
        "transaction": "|15254,",
        "type": "FREE_AGENT",
        "franchise": "0005"
      },
      {
        "type": "FREE_AGENT",
        "franchise": "0005",
        "transaction": "|14800,",
        "timestamp": "1783954476"
      },
      {
        "timestamp": "1783954475",
        "transaction": "|13610,",
        "franchise": "0005",
        "type": "FREE_AGENT"
      },
      {
        "franchise": "0005",
        "type": "FREE_AGENT",
        "transaction": "|15258,",
        "timestamp": "1783954475"
      },
      {
        "franchise": "0005",
        "type": "FREE_AGENT",
        "transaction": "|15712,",
        "timestamp": "1783954473"
      },
      {
        "timestamp": "1783954471",
        "franchise": "0005",
        "type": "FREE_AGENT",
        "transaction": "|13592,"
      },
      {
        "timestamp": "1783954469",
        "transaction": "|0515,",
        "type": "FREE_AGENT",
        "franchise": "0004"
      },
      {
        "timestamp": "1783954463",
        "transaction": "|16649,",
        "franchise": "0004",
        "type": "FREE_AGENT"
      },
      {
        "timestamp": "1783954454",
        "franchise": "0004",
        "type": "FREE_AGENT",
        "transaction": "|17254,"
      },
      {
        "transaction": "|16619,",
        "franchise": "0004",
        "type": "FREE_AGENT",
        "timestamp": "1783954447"
      },
      {
        "franchise": "0004",
        "type": "FREE_AGENT",
        "transaction": "|17047,",
        "timestamp": "1783954438"
      },
      {
        "franchise": "0004",
        "type": "FREE_AGENT",
        "transaction": "|15255,",
        "timestamp": "1783954429"
      },
      {
        "timestamp": "1783954418",
        "franchise": "0004",
        "type": "FREE_AGENT",
        "transaction": "|17256,"
      },
      {
        "transaction": "|14833,",
        "type": "FREE_AGENT",
        "franchise": "0004",
        "timestamp": "1783954133"
      },
      {
        "timestamp": "1783950714",
        "franchise": "0014",
        "type": "FREE_AGENT",
        "transaction": "|16593,17075,"
      },
      {
        "transaction": "|14842,",
        "franchise": "0013",
        "type": "FREE_AGENT",
        "timestamp": "1783865070"
      },
      {
        "type": "FREE_AGENT",
        "franchise": "0013",
        "transaction": "|17256,",
        "timestamp": "1783865029"
      },
      {
        "transaction": "|16214,",
        "franchise": "0009",
        "type": "FREE_AGENT",
        "timestamp": "1783744781"
      },
      {
        "timestamp": "1783744650",
        "type": "FREE_AGENT",
        "franchise": "0009",
        "transaction": "|14777,"
      },
      {
        "transaction": "|12186,14840,17053,",
        "type": "FREE_AGENT",
        "franchise": "0014",
        "timestamp": "1783485443"
      },
      {
        "type": "FREE_AGENT",
        "franchise": "0007",
        "transaction": "|12611,16584,13138,15293,16778,14860,16723,14867,15979,0521,0511,",
        "timestamp": "1783188998"
      },
      {
        "transaction": "|16680,",
        "franchise": "0004",
        "type": "FREE_AGENT",
        "timestamp": "1783174607"
      },
      {
        "transaction": "|17105,",
        "franchise": "0004",
        "type": "FREE_AGENT",
        "timestamp": "1783174600"
      },
      {
        "timestamp": "1783150758",
        "transaction": "|16184,",
        "type": "FREE_AGENT",
        "franchise": "0009"
      },
      {
        "timestamp": "1783150739",
        "transaction": "|13630,",
        "franchise": "0009",
        "type": "FREE_AGENT"
      },
      {
        "timestamp": "1783150716",
        "transaction": "|15259,",
        "franchise": "0009",
        "type": "FREE_AGENT"
      },
      {
        "transaction": "|13193,",
        "franchise": "0009",
        "type": "FREE_AGENT",
        "timestamp": "1783150697"
      },
      {
        "franchise": "0009",
        "type": "FREE_AGENT",
        "transaction": "|9064,",
        "timestamp": "1783146426"
      },
      {
        "transaction": "|16287,",
        "franchise": "0009",
        "type": "FREE_AGENT",
        "timestamp": "1783146375"
      },
      {
        "timestamp": "1783141098",
        "franchise": "0021",
        "type": "FREE_AGENT",
        "transaction": "|12263,12956,0515,16595,"
      },
      {
        "transaction": "|0507,",
        "franchise": "0020",
        "type": "FREE_AGENT",
        "timestamp": "1783088855"
      },
      {
        "transaction": "|16846,",
        "franchise": "0020",
        "type": "FREE_AGENT",
        "timestamp": "1783088854"
      },
      {
        "timestamp": "1783088853",
        "transaction": "|13189,",
        "type": "FREE_AGENT",
        "franchise": "0020"
      },
      {
        "type": "FREE_AGENT",
        "franchise": "0020",
        "transaction": "|16620,",
        "timestamp": "1783088852"
      },
      {
        "transaction": "|15789,",
        "franchise": "0020",
        "type": "FREE_AGENT",
        "timestamp": "1783088850"
      },
      {
        "timestamp": "1783088849",
        "type": "FREE_AGENT",
        "franchise": "0020",
        "transaction": "|16616,"
      },
      {
        "timestamp": "1783088848",
        "transaction": "|16610,",
        "type": "FREE_AGENT",
        "franchise": "0020"
      },
      {
        "timestamp": "1783088847",
        "type": "FREE_AGENT",
        "franchise": "0020",
        "transaction": "|17059,"
      },
      {
        "timestamp": "1783088847",
        "transaction": "|13116,",
        "franchise": "0020",
        "type": "FREE_AGENT"
      },
      {
        "type": "FREE_AGENT",
        "franchise": "0020",
        "transaction": "|12616,",
        "timestamp": "1783088846"
      },
      {
        "transaction": "|0529,",
        "franchise": "0017",
        "type": "FREE_AGENT",
        "timestamp": "1783074954"
      },
      {
        "timestamp": "1783074953",
        "type": "FREE_AGENT",
        "franchise": "0017",
        "transaction": "|11936,"
      },
      {
        "type": "FREE_AGENT",
        "franchise": "0017",
        "transaction": "|13772,",
        "timestamp": "1783074952"
      },
      {
        "timestamp": "1783074948",
        "franchise": "0017",
        "type": "FREE_AGENT",
        "transaction": "|11244,"
      },
      {
        "timestamp": "1783074948",
        "franchise": "0017",
        "type": "FREE_AGENT",
        "transaction": "|15284,"
      },
      {
        "timestamp": "1783074947",
        "type": "FREE_AGENT",
        "franchise": "0017",
        "transaction": "|15757,"
      },
      {
        "timestamp": "1783074946",
        "franchise": "0017",
        "type": "FREE_AGENT",
        "transaction": "|14127,"
      },
      {
        "timestamp": "1783074945",
        "transaction": "|15727,",
        "type": "FREE_AGENT",
        "franchise": "0017"
      },
      {
        "franchise": "0017",
        "type": "FREE_AGENT",
        "transaction": "|17030,",
        "timestamp": "1783074941"
      },
      {
        "timestamp": "1782415447",
        "transaction": "|16212,",
        "type": "FREE_AGENT",
        "franchise": "0024"
      },
      {
        "franchise": "0024",
        "type": "FREE_AGENT",
        "transaction": "|17106,",
        "timestamp": "1782415397"
      },
      {
        "timestamp": "1782415384",
        "type": "FREE_AGENT",
        "franchise": "0024",
        "transaction": "|0523,"
      },
      {
        "transaction": "|14833,",
        "type": "FREE_AGENT",
        "franchise": "0024",
        "timestamp": "1782415352"
      },
      {
        "timestamp": "1782415291",
        "franchise": "0024",
        "type": "FREE_AGENT",
        "transaction": "|16649,"
      },
      {
        "franchise": "0024",
        "type": "FREE_AGENT",
        "transaction": "|12860,",
        "timestamp": "1782415276"
      },
      {
        "franchise": "0024",
        "type": "FREE_AGENT",
        "transaction": "|0530,",
        "timestamp": "1782415253"
      },
      {
        "transaction": "|17134,",
        "franchise": "0024",
        "type": "FREE_AGENT",
        "timestamp": "1782415240"
      },
      {
        "type": "FREE_AGENT",
        "franchise": "0024",
        "transaction": "|17062,",
        "timestamp": "1782415228"
      },
      {
        "type": "FREE_AGENT",
        "franchise": "0015",
        "transaction": "|16628,15368,16896,0509,0522,",
        "timestamp": "1782398068"
      },
      {
        "type": "FREE_AGENT",
        "franchise": "0001",
        "transaction": "|17222,",
        "timestamp": "1782360677"
      },
      {
        "type": "FREE_AGENT",
        "franchise": "0001",
        "transaction": "|14983,",
        "timestamp": "1782360067"
      },
      {
        "franchise": "0001",
        "type": "FREE_AGENT",
        "transaction": "|0514,",
        "timestamp": "1782357294"
      },
      {
        "timestamp": "1782352623",
        "type": "FREE_AGENT",
        "franchise": "0001",
        "transaction": "|17039,"
      },
      {
        "timestamp": "1782160094",
        "type": "FREE_AGENT",
        "franchise": "0009",
        "transaction": "|15368,"
      },
      {
        "transaction": "|0503,",
        "type": "FREE_AGENT",
        "franchise": "0009",
        "timestamp": "1782160081"
      }
    ]
  },
  "encoding": "utf-8"
}