{
  "version": "1.0",
  "leagueStandings": {
    "franchise": [
      {
        "ww": "16",
        "nondivw": "10",
        "h2hl": "3",
        "h2hw": "15",
        "h2ht": "0",
        "salary": "$35012147.50",
        "dp": "181.03",
        "divwlt": "5-1-0",
        "all_play_pct": ".659",
        "nondivl": "2",
        "eff": "86.9",
        "bbidspent": "$45000000.00",
        "pa": "1592.99",
        "op": "1817.33",
        "divpct": ".833",
        "add_count": "0",
        "maxpa": "118.25",
        "acct": "$62.00",
        "strk": "L1",
        "divpf": "710.31",
        "minpf": "62.48",
        "id": "0009",
        "pf": "1998.36",
        "altpwr": "45.0",
        "h2hwlt": "15-3-0",
        "nondivt": "0",
        "bbidbalance": "$9987852.50",
        "pp": "2299.27",
        "waiver_add_count": "0",
        "nondivwlt": "10-2-0",
        "eliminated": "",
        "divt": "0",
        "divw": "5",
        "pwr": "40.31",
        "avgpa": "88.5",
        "divl": "1",
        "nondivpct": ".833",
        "minpa": "31.3",
        "vp": "51",
        "h2hpct": ".833",
        "maxpf": "168.16",
        "fname": "Wascawy Wabbits",
        "avgpf": "117.6",
        "all_play_wlt": "168-87-0"
      },
      {
        "nondivl": "3",
        "all_play_pct": ".675",
        "divwlt": "5-1-0",
        "dp": "179.40",
        "salary": "$38912910.25",
        "h2ht": "0",
        "h2hw": "14",
        "h2hl": "4",
        "nondivw": "9",
        "ww": "15",
        "add_count": "0",
        "divpct": ".833",
        "op": "1781.70",
        "pa": "1754.87",
        "bbidspent": "$45000000.00",
        "eff": "85.5",
        "divl": "1",
        "avgpa": "97.5",
        "pwr": "40.49",
        "divw": "5",
        "divt": "0",
        "nondivwlt": "9-3-0",
        "eliminated": "",
        "waiver_add_count": "0",
        "pp": "2294.10",
        "bbidbalance": "$6087089.75",
        "nondivt": "0",
        "h2hwlt": "14-4-0",
        "altpwr": "43.0",
        "pf": "1961.10",
        "id": "0015",
        "minpf": "69.89",
        "divpf": "716.86",
        "strk": "W1",
        "acct": "$50.00",
        "maxpa": "138.2",
        "all_play_wlt": "172-83-0",
        "avgpf": "115.4",
        "maxpf": "172.47",
        "fname": "Dark Magicians of Chaos",
        "h2hpct": ".778",
        "minpa": "54.35",
        "vp": "52",
        "nondivpct": ".750"
      },
      {
        "avgpf": "117.2",
        "all_play_wlt": "181-74-0",
        "nondivpct": ".833",
        "minpa": "72.17",
        "vp": "53",
        "h2hpct": ".722",
        "fname": "Da Dangsters",
        "maxpf": "146.08",
        "bbidbalance": "$9251999.25",
        "pp": "2386.78",
        "waiver_add_count": "0",
        "nondivwlt": "10-2-0",
        "eliminated": "",
        "divw": "3",
        "divt": "0",
        "pwr": "38.75",
        "avgpa": "99.5",
        "divl": "3",
        "maxpa": "138.9",
        "acct": "$50.00",
        "strk": "L1",
        "minpf": "58.29",
        "id": "0002",
        "divpf": "607.76",
        "pf": "1992.84",
        "altpwr": "44.5",
        "h2hwlt": "13-5-0",
        "nondivt": "0",
        "op": "1796.24",
        "divpct": ".500",
        "add_count": "0",
        "eff": "83.5",
        "bbidspent": "$45000000.00",
        "pa": "1791.48",
        "salary": "$35748000.75",
        "dp": "196.60",
        "divwlt": "3-3-0",
        "all_play_pct": ".710",
        "nondivl": "2",
        "ww": "14",
        "nondivw": "10",
        "h2hl": "5",
        "h2ht": "0",
        "h2hw": "13"
      },
      {
        "pa": "1730.50",
        "eff": "87.3",
        "bbidspent": "$45000000.00",
        "divpct": ".333",
        "add_count": "0",
        "op": "1709.79",
        "h2hl": "5",
        "h2ht": "0",
        "h2hw": "13",
        "ww": "13",
        "nondivw": "11",
        "dp": "161.40",
        "salary": "$38534824.00",
        "divwlt": "2-4-0",
        "nondivl": "1",
        "all_play_pct": ".588",
        "minpa": "65.2",
        "vp": "47",
        "h2hpct": ".722",
        "fname": "Computer Jocks",
        "maxpf": "166.14",
        "nondivpct": ".917",
        "avgpf": "110.1",
        "all_play_wlt": "150-105-0",
        "h2hwlt": "13-5-0",
        "nondivt": "0",
        "maxpa": "135.2",
        "strk": "L1",
        "acct": "$50.00",
        "pf": "1871.19",
        "altpwr": "35.5",
        "id": "0010",
        "divpf": "673.25",
        "minpf": "73.07",
        "nondivwlt": "11-1-0",
        "eliminated": "",
        "waiver_add_count": "0",
        "pwr": "34.34",
        "divt": "0",
        "divw": "2",
        "avgpa": "96.1",
        "divl": "4",
        "pp": "2142.68",
        "bbidbalance": "$6465176.00"
      },
      {
        "h2ht": "0",
        "h2hw": "12",
        "h2hl": "6",
        "nondivw": "8",
        "ww": "12",
        "nondivl": "4",
        "all_play_pct": ".698",
        "divwlt": "4-2-0",
        "dp": "212.25",
        "salary": "$30893108.50",
        "pa": "1742.40",
        "bbidspent": "$45000000.00",
        "eff": "86.5",
        "add_count": "0",
        "divpct": ".667",
        "op": "1741.63",
        "nondivt": "0",
        "h2hwlt": "12-6-0",
        "altpwr": "40.0",
        "pf": "1953.88",
        "minpf": "80.81",
        "id": "0012",
        "divpf": "685.35",
        "strk": "W3",
        "acct": "$48.00",
        "maxpa": "134.4",
        "divl": "2",
        "avgpa": "96.8",
        "pwr": "37.81",
        "divw": "4",
        "divt": "0",
        "eliminated": "",
        "nondivwlt": "8-4-0",
        "waiver_add_count": "0",
        "pp": "2258.97",
        "bbidbalance": "$14106891.50",
        "fname": "Vitside Mafia",
        "maxpf": "140.70",
        "h2hpct": ".667",
        "vp": "50",
        "minpa": "31.3",
        "nondivpct": ".667",
        "all_play_wlt": "178-77-0",
        "avgpf": "114.9"
      },
      {
        "divpct": "1.000",
        "add_count": "0",
        "all_play_wlt": "157-98-0",
        "avgpf": "111.5",
        "op": "1737.27",
        "h2hpct": ".611",
        "pa": "1911.02",
        "fname": "Bring the Pain",
        "maxpf": "195.26",
        "minpa": "76.41",
        "vp": "44",
        "bbidspent": "$45000000.00",
        "nondivpct": ".417",
        "eff": "84.9",
        "divwlt": "6-0-0",
        "avgpa": "106.2",
        "all_play_pct": ".616",
        "nondivl": "7",
        "divl": "0",
        "waiver_add_count": "0",
        "salary": "$42814161.25",
        "eliminated": "",
        "nondivwlt": "5-7-0",
        "dp": "158.00",
        "divt": "0",
        "divw": "6",
        "pwr": "37.50",
        "bbidbalance": "$2185838.75",
        "pp": "2232.76",
        "h2ht": "0",
        "h2hw": "11",
        "h2hwlt": "11-7-0",
        "nondivt": "0",
        "h2hl": "7",
        "nondivw": "5",
        "divpf": "766.09",
        "minpf": "58.89",
        "id": "0008",
        "altpwr": "34.5",
        "pf": "1895.27",
        "maxpa": "166.14",
        "ww": "11",
        "acct": "$50.00",
        "strk": "W4"
      },
      {
        "maxpa": "139.25",
        "ww": "10",
        "strk": "W1",
        "acct": "$25.00",
        "nondivw": "8",
        "pf": "1613.30",
        "altpwr": "22.5",
        "id": "0001",
        "divpf": "514.9",
        "minpf": "31.30",
        "h2hwlt": "11-7-0",
        "nondivt": "0",
        "h2hl": "7",
        "h2hw": "11",
        "h2ht": "0",
        "pp": "1885.29",
        "bbidbalance": "$15865134.75",
        "dp": "137.80",
        "eliminated": "",
        "nondivwlt": "8-4-0",
        "salary": "$29134865.25",
        "waiver_add_count": "0",
        "pwr": "29.55",
        "divt": "0",
        "divw": "3",
        "avgpa": "96.5",
        "divwlt": "3-3-0",
        "divl": "3",
        "nondivl": "4",
        "all_play_pct": ".431",
        "eff": "85.6",
        "bbidspent": "$45000000.00",
        "nondivpct": ".667",
        "vp": "38",
        "minpa": "54.75",
        "h2hpct": ".611",
        "fname": "Pacific Pigskins",
        "maxpf": "141.04",
        "pa": "1737.24",
        "op": "1475.50",
        "avgpf": "94.9",
        "all_play_wlt": "110-145-0",
        "divpct": ".500",
        "add_count": "0"
      },
      {
        "op": "1678.58",
        "avgpf": "108.6",
        "all_play_wlt": "148-107-0",
        "divpct": ".500",
        "add_count": "0",
        "eff": "82.3",
        "bbidspent": "$45000000.00",
        "nondivpct": ".583",
        "minpa": "57.59",
        "vp": "41",
        "h2hpct": ".556",
        "fname": "Gridiron Geeks",
        "maxpf": "143.19",
        "pa": "1880.64",
        "pp": "2243.79",
        "bbidbalance": "$14402350.50",
        "dp": "167.00",
        "eliminated": "",
        "nondivwlt": "7-5-0",
        "waiver_add_count": "0",
        "salary": "$30597649.50",
        "pwr": "33.69",
        "divt": "0",
        "divw": "3",
        "avgpa": "104.5",
        "divwlt": "3-3-0",
        "nondivl": "5",
        "divl": "3",
        "all_play_pct": ".580",
        "maxpa": "168.16",
        "ww": "9",
        "strk": "W3",
        "acct": "$50.00",
        "nondivw": "7",
        "altpwr": "29.0",
        "pf": "1845.58",
        "minpf": "73.96",
        "id": "0013",
        "divpf": "623.66",
        "h2hwlt": "10-8-0",
        "h2hl": "8",
        "nondivt": "0",
        "h2ht": "0",
        "h2hw": "10"
      },
      {
        "divt": "0",
        "divw": "5",
        "pwr": "31.27",
        "waiver_add_count": "0",
        "salary": "$27966679.25",
        "nondivwlt": "4-8-0",
        "dp": "190.79",
        "eliminated": "",
        "all_play_pct": ".463",
        "nondivl": "8",
        "divl": "1",
        "divwlt": "5-1-0",
        "avgpa": "92.4",
        "bbidbalance": "$17033320.75",
        "pp": "2108.99",
        "h2hl": "9",
        "nondivt": "0",
        "h2hwlt": "9-9-0",
        "h2ht": "0",
        "h2hw": "9",
        "acct": "$59.00",
        "strk": "W1",
        "ww": "8",
        "maxpa": "141.04",
        "divpf": "668.38",
        "id": "0011",
        "minpf": "54.35",
        "altpwr": "22.0",
        "pf": "1665.88",
        "nondivw": "4",
        "add_count": "0",
        "divpct": ".833",
        "avgpf": "98.0",
        "op": "1475.09",
        "all_play_wlt": "118-137-0",
        "vp": "32",
        "minpa": "62.48",
        "pa": "1662.33",
        "fname": "Midwestside Connection",
        "maxpf": "144.74",
        "h2hpct": ".500",
        "eff": "79.0",
        "nondivpct": ".333",
        "bbidspent": "$45000000.00"
      },
      {
        "h2ht": "0",
        "h2hw": "8",
        "h2hwlt": "8-10-0",
        "h2hl": "10",
        "nondivt": "0",
        "nondivw": "5",
        "altpwr": "25.0",
        "pf": "1751.97",
        "minpf": "54.75",
        "divpf": "635.73",
        "id": "0005",
        "ww": "7",
        "maxpa": "166.03",
        "strk": "W3",
        "acct": "$50.00",
        "avgpa": "97.7",
        "divwlt": "3-3-0",
        "divl": "3",
        "nondivl": "7",
        "all_play_pct": ".498",
        "dp": "148.80",
        "eliminated": "",
        "nondivwlt": "5-7-0",
        "salary": "$41116945.00",
        "waiver_add_count": "0",
        "pwr": "29.89",
        "divt": "0",
        "divw": "3",
        "pp": "2167.79",
        "bbidbalance": "$3883055.00",
        "h2hpct": ".444",
        "fname": "The Mariachi Ninjas",
        "maxpf": "153.55",
        "pa": "1758.39",
        "vp": "32",
        "minpa": "62.13",
        "bbidspent": "$45000000.00",
        "nondivpct": ".417",
        "eff": "80.8",
        "divpct": ".500",
        "add_count": "0",
        "all_play_wlt": "127-128-0",
        "op": "1603.17",
        "avgpf": "103.1"
      },
      {
        "divl": "4",
        "avgpa": "109.9",
        "divt": "0",
        "divw": "2",
        "pwr": "25.34",
        "waiver_add_count": "0",
        "nondivwlt": "4-8-0",
        "eliminated": "",
        "bbidbalance": "$6214972.00",
        "pp": "2118.83",
        "nondivt": "0",
        "h2hwlt": "6-12-0",
        "id": "0016",
        "minpf": "70.85",
        "divpf": "611.91",
        "altpwr": "22.0",
        "pf": "1746.95",
        "acct": "$53.00",
        "strk": "W1",
        "maxpa": "144.09",
        "all_play_wlt": "126-129-0",
        "avgpf": "102.8",
        "maxpf": "170.82",
        "fname": " Running Down The Dream",
        "h2hpct": ".333",
        "vp": "28",
        "minpa": "63.21",
        "nondivpct": ".333",
        "all_play_pct": ".494",
        "nondivl": "8",
        "divwlt": "2-4-0",
        "salary": "$38785028.00",
        "dp": "113.00",
        "h2hw": "6",
        "h2ht": "0",
        "h2hl": "12",
        "nondivw": "4",
        "ww": "6",
        "add_count": "0",
        "divpct": ".333",
        "op": "1633.95",
        "pa": "1978.11",
        "bbidspent": "$45000000.00",
        "eff": "82.4"
      },
      {
        "maxpa": "157.21",
        "strk": "L3",
        "acct": "$0.00",
        "pf": "1544.42",
        "altpwr": "10.5",
        "divpf": "578.11",
        "id": "0014",
        "minpf": "59.96",
        "h2hwlt": "5-13-0",
        "nondivt": "0",
        "pp": "1831.82",
        "bbidbalance": "$11542195.00",
        "nondivwlt": "2-10-0",
        "eliminated": "",
        "waiver_add_count": "0",
        "pwr": "22.27",
        "divw": "3",
        "divt": "0",
        "avgpa": "111.2",
        "divl": "3",
        "nondivpct": ".167",
        "minpa": "61.09",
        "vp": "20",
        "h2hpct": ".278",
        "maxpf": "128.58",
        "fname": "Cowboy Up",
        "avgpf": "90.8",
        "all_play_wlt": "86-169-0",
        "ww": "5",
        "nondivw": "2",
        "h2hl": "13",
        "h2ht": "0",
        "h2hw": "5",
        "dp": "38.75",
        "salary": "$33457805.00",
        "divwlt": "3-3-0",
        "nondivl": "10",
        "all_play_pct": ".337",
        "eff": "84.3",
        "bbidspent": "$45000000.00",
        "pa": "2001.75",
        "op": "1505.67",
        "divpct": ".500",
        "add_count": "0"
      },
      {
        "op": "1411.78",
        "divpct": ".333",
        "add_count": "0",
        "eff": "81.2",
        "bbidspent": "$45000000.00",
        "pa": "1936.22",
        "salary": "$28812530.00",
        "dp": "114.47",
        "divwlt": "2-4-0",
        "all_play_pct": ".349",
        "nondivl": "9",
        "ww": "4",
        "nondivw": "3",
        "h2hl": "13",
        "h2hw": "5",
        "h2ht": "0",
        "avgpf": "89.8",
        "all_play_wlt": "89-166-0",
        "nondivpct": ".250",
        "minpa": "70.8",
        "vp": "22",
        "h2hpct": ".278",
        "maxpf": "130.36",
        "fname": "The Music City Mafia",
        "bbidbalance": "$16187470.00",
        "pp": "1878.77",
        "waiver_add_count": "0",
        "eliminated": "",
        "nondivwlt": "3-9-0",
        "divw": "2",
        "divt": "0",
        "pwr": "21.82",
        "avgpa": "107.6",
        "divl": "4",
        "maxpa": "137.54",
        "acct": "$50.00",
        "strk": "L2",
        "minpf": "42.61",
        "divpf": "569.8",
        "id": "0006",
        "pf": "1526.25",
        "altpwr": "11.0",
        "h2hwlt": "5-13-0",
        "nondivt": "0"
      },
      {
        "avgpf": "88.4",
        "all_play_wlt": "73-182-0",
        "nondivpct": ".250",
        "vp": "20",
        "minpa": "58.89",
        "h2hpct": ".278",
        "fname": "Dead Cap Walking ",
        "maxpf": "137.80",
        "bbidbalance": "$9218697.75",
        "pp": "1788.82",
        "waiver_add_count": "0",
        "eliminated": "",
        "nondivwlt": "3-9-0",
        "divw": "2",
        "divt": "0",
        "pwr": "19.77",
        "avgpa": "100.2",
        "divl": "4",
        "maxpa": "144.74",
        "acct": "$0.00",
        "strk": "L3",
        "minpf": "45.96",
        "id": "0004",
        "divpf": "531.6",
        "pf": "1503.05",
        "altpwr": "7.5",
        "h2hwlt": "5-13-0",
        "nondivt": "0",
        "op": "1390.46",
        "divpct": ".333",
        "add_count": "0",
        "eff": "84.0",
        "bbidspent": "$45000000.00",
        "pa": "1804.50",
        "salary": "$35781302.25",
        "dp": "112.59",
        "divwlt": "2-4-0",
        "all_play_pct": ".286",
        "nondivl": "9",
        "ww": "2",
        "nondivw": "3",
        "h2hl": "13",
        "h2hw": "5",
        "h2ht": "0"
      },
      {
        "pp": "2026.41",
        "bbidbalance": "$15760700.00",
        "eliminated": "",
        "dp": "113.60",
        "nondivwlt": "5-7-0",
        "waiver_add_count": "0",
        "salary": "$29239300.00",
        "pwr": "20.66",
        "divw": "0",
        "divt": "0",
        "avgpa": "109.7",
        "divwlt": "0-6-0",
        "divl": "6",
        "nondivl": "7",
        "all_play_pct": ".349",
        "maxpa": "141.44",
        "ww": "3",
        "strk": "L1",
        "acct": "$52.00",
        "nondivw": "5",
        "pf": "1571.94",
        "altpwr": "13.0",
        "id": "0003",
        "minpf": "61.09",
        "divpf": "508.16",
        "h2hwlt": "5-13-0",
        "h2hl": "13",
        "nondivt": "0",
        "h2ht": "0",
        "h2hw": "5",
        "op": "1458.34",
        "avgpf": "92.5",
        "all_play_wlt": "89-166-0",
        "divpct": ".000",
        "add_count": "0",
        "eff": "77.6",
        "bbidspent": "$45000000.00",
        "nondivpct": ".417",
        "minpa": "70.8",
        "vp": "20",
        "h2hpct": ".278",
        "fname": "Maverick",
        "maxpf": "128.55",
        "pa": "1973.80"
      },
      {
        "waiver_add_count": "0",
        "nondivwlt": "2-10-0",
        "eliminated": "",
        "divt": "0",
        "divw": "0",
        "pwr": "15.75",
        "avgpa": "115.2",
        "divl": "6",
        "bbidbalance": "$9664438.00",
        "pp": "1797.11",
        "h2hwlt": "2-16-0",
        "nondivt": "0",
        "maxpa": "195.26",
        "acct": "$0.00",
        "strk": "L7",
        "divpf": "465.47",
        "id": "0007",
        "minpf": "57.59",
        "pf": "1453.35",
        "altpwr": "3.0",
        "avgpf": "85.5",
        "all_play_wlt": "68-187-0",
        "minpa": "45.96",
        "vp": "10",
        "h2hpct": ".111",
        "maxpf": "118.92",
        "fname": "Fire Ready Aim",
        "nondivpct": ".167",
        "salary": "$35335562.00",
        "dp": "161.42",
        "divwlt": "0-6-0",
        "all_play_pct": ".267",
        "nondivl": "10",
        "h2hl": "16",
        "h2hw": "2",
        "h2ht": "0",
        "ww": "1",
        "nondivw": "2",
        "divpct": ".000",
        "add_count": "0",
        "op": "1291.93",
        "pa": "2073.99",
        "eff": "80.9",
        "bbidspent": "$45000000.00"
      }
    ]
  },
  "encoding": "utf-8"
}